pyhatchery/__about__.py
pyhatchery/__init__.py
pyhatchery/__main__.py
pyhatchery/cli.py
pyhatchery/components/__init__.py
pyhatchery/components/config_loader.py
pyhatchery/components/http_client.py
pyhatchery/components/interactive_wizard.py
pyhatchery/components/name_service.py
pyhatchery/components/project_generator.py
pyhatchery/utils/__init__.py
pyhatchery/utils/config.py
pyhatchery-0.9.1.dist-info/METADATA
pyhatchery-0.9.1.dist-info/WHEEL
pyhatchery-0.9.1.dist-info/entry_points.txt
pyhatchery-0.9.1.dist-info/licenses/LICENSE
pyhatchery-0.9.1.dist-info/RECORD
