Metadata-Version: 2.4
Name: pyhatchery
Version: 0.9.1
Summary: PyHatchery: A Python project scaffolding tool.
Project-URL: Homepage, https://github.com/ksylvan/pyhatchery
Project-URL: Releases, https://github.com/ksylvan/pyhatchery/releases
Project-URL: Bug Tracker, https://github.com/ksylvan/pyhatchery/issues
Project-URL: Documentation, https://github.com/ksylvan/pyhatchery#readme
Author-email: Kayvan Sylvan <kayvan@sylvan.com>
License: MIT
License-File: LICENSE
Classifier: License :: OSI Approved :: MIT License
Classifier: Operating System :: OS Independent
Classifier: Programming Language :: Python :: 3
Requires-Python: >=3.11
Requires-Dist: click>=8.2.0
Requires-Dist: python-dotenv>=1.1.0
Requires-Dist: requests>=2.32.3
